[
  {
    "id": 71399,
    "cover": {
      "id": 66956,
      "game": 71399,
      "height": 678,
      "image_id": "a18odqqdotlvajaodncx",
      "url": "//images.igdb.com/igdb/image/upload/t_thumb/a18odqqdotlvajaodncx.jpg",
      "width": 800
    },
    "first_release_date": 843782400,
    "game_modes": [
      {
        "id": 1,
        "name": "Single player"
      }
    ],
    "name": "Sakura Taisen",
    "popularity": 1.428449549854386,
    "screenshots": [
      {
        "id": 215347,
        "game": 71399,
        "height": 225,
        "image_id": "rv65xcyj74sv4lcfjzfa",
        "url": "//images.igdb.com/igdb/image/upload/t_thumb/rv65xcyj74sv4lcfjzfa.jpg",
        "width": 300
      },
      {
        "id": 215348,
        "game": 71399,
        "height": 247,
        "image_id": "ifrdu9mwzidso1x4spwb",
        "url": "//images.igdb.com/igdb/image/upload/t_thumb/ifrdu9mwzidso1x4spwb.jpg",
        "width": 320
      }
    ],
    "slug": "sakura-taisen",
    "summary": "Released in 1996 for the Sega Saturn, Sakura Taisen is the first game in the iconic Japanese game franchise. It combines strategy RPG elements with dating sim-style character interactions to make \"A Storm of Romance amid Taishou Cherry Blossoms!\""
  }
]